odoo10_addon_sale_commission_areamanager-10.0.1.1.0-py2.7-nspkg.pth
odoo/addons/sale_commission_areamanager/README.rst
odoo/addons/sale_commission_areamanager/__init__.py
odoo/addons/sale_commission_areamanager/__manifest__.py
odoo/addons/sale_commission_areamanager/i18n/es.po
odoo/addons/sale_commission_areamanager/i18n/fr.po
odoo/addons/sale_commission_areamanager/i18n/it.po
odoo/addons/sale_commission_areamanager/i18n/sale_commission_areamanager.pot
odoo/addons/sale_commission_areamanager/i18n/tr.po
odoo/addons/sale_commission_areamanager/models/__init__.py
odoo/addons/sale_commission_areamanager/models/account_invoice.py
odoo/addons/sale_commission_areamanager/models/res_partner.py
odoo/addons/sale_commission_areamanager/models/sale_order.py
odoo/addons/sale_commission_areamanager/readme/CONTRIBUTORS.rst
odoo/addons/sale_commission_areamanager/readme/CREDITS.rst
odoo/addons/sale_commission_areamanager/readme/DESCRIPTION.rst
odoo/addons/sale_commission_areamanager/readme/USAGE.rst
odoo/addons/sale_commission_areamanager/static/description/icon.png
odoo/addons/sale_commission_areamanager/static/description/index.html
odoo/addons/sale_commission_areamanager/tests/__init__.py
odoo/addons/sale_commission_areamanager/tests/areamanager_test.py
odoo/addons/sale_commission_areamanager/views/res_partner_view.xml
odoo10_addon_sale_commission_areamanager-10.0.1.1.0.dist-info/METADATA
odoo10_addon_sale_commission_areamanager-10.0.1.1.0.dist-info/RECORD
odoo10_addon_sale_commission_areamanager-10.0.1.1.0.dist-info/WHEEL
odoo10_addon_sale_commission_areamanager-10.0.1.1.0.dist-info/namespace_packages.txt
odoo10_addon_sale_commission_areamanager-10.0.1.1.0.dist-info/top_level.txt
